particle/__init__.py
particle/main.py
particle.io-0.0.1.dist-info/LICENSE
particle.io-0.0.1.dist-info/METADATA
particle.io-0.0.1.dist-info/WHEEL
particle.io-0.0.1.dist-info/top_level.txt
particle.io-0.0.1.dist-info/RECORD
